lambda_otel_lite/.gitignore
lambda_otel_lite/__init__.py
lambda_otel_lite/config.py
lambda_otel_lite/constants.py
lambda_otel_lite/extension.py
lambda_otel_lite/extractors.py
lambda_otel_lite/handler.py
lambda_otel_lite/logger.py
lambda_otel_lite/processor.py
lambda_otel_lite/propagation.py
lambda_otel_lite/py.typed
lambda_otel_lite/resource.py
lambda_otel_lite/telemetry.py
lambda_otel_lite/version.py
lambda_otel_lite-0.15.0.dist-info/METADATA
lambda_otel_lite-0.15.0.dist-info/WHEEL
lambda_otel_lite-0.15.0.dist-info/licenses/LICENSE
lambda_otel_lite-0.15.0.dist-info/RECORD
