Metadata-Version: 2.4
Name: lambda_otel_lite
Version: 0.15.0
Summary: Lightweight OpenTelemetry instrumentation for AWS Lambda
Project-URL: Homepage, https://github.com/dev7a/serverless-otlp-forwarder
Project-URL: Repository, https://github.com/dev7a/serverless-otlp-forwarder/tree/main/packages/python/lambda-otel-lite
Author-email: Alessandro Bologna <alessandro.bologna@gmail.com>
License: MIT
License-File: LICENSE
Keywords: aws,lambda,opentelemetry,otel,tracing
Classifier: Development Status :: 3 - Alpha
Classifier: Intended Audience :: Developers
Classifier: License :: OSI Approved :: Apache Software License
Classifier: Programming Language :: Python :: 3.12
Classifier: Topic :: Software Development :: Libraries :: Python Modules
Classifier: Topic :: System :: Monitoring
Requires-Python: >=3.12
Requires-Dist: opentelemetry-api>=1.32.1
Requires-Dist: opentelemetry-propagator-aws-xray>=1.0.0
Requires-Dist: opentelemetry-sdk>=1.32.1
Requires-Dist: otlp-stdout-span-exporter>=0.15.0
Provides-Extra: dev
Requires-Dist: mypy>=1.14.0; extra == 'dev'
Requires-Dist: pytest-cov>=4.1.0; extra == 'dev'
Requires-Dist: pytest>=7.4.0; extra == 'dev'
Requires-Dist: ruff>=0.1.0; extra == 'dev'
Provides-Extra: otlp-http
Requires-Dist: opentelemetry-exporter-otlp-proto-http>=1.30.0; extra == 'otlp-http'
